logging518/__init__.py
logging518/config.py
logging518/py.typed
logging518-1.0.0.dist-info/LICENSE
logging518-1.0.0.dist-info/WHEEL
logging518-1.0.0.dist-info/METADATA
logging518-1.0.0.dist-info/RECORD
