Metadata-Version: 2.1
Name: logging518
Version: 1.0.0
Summary: Configure Python's native logging module using pyproject.toml
Home-page: https://github.com/mharrisb1/logging518
License: MIT
Author: Michael Harris
Author-email: michael.harrisru@gmail.com
Requires-Python: >=3.7,<4.0
Classifier: License :: OSI Approved :: MIT License
Classifier: Programming Language :: Python :: 3
Classifier: Programming Language :: Python :: 3.10
Classifier: Programming Language :: Python :: 3.7
Classifier: Programming Language :: Python :: 3.8
Classifier: Programming Language :: Python :: 3.9
Requires-Dist: tomli (>=2.0.1,<3.0.0); python_version < "3.11"
Project-URL: Repository, https://github.com/mharrisb1/logging518
